{
  "gitSyncId": "686f90591e05f26da4df0c0b_fa486877-5136-471a-8d08-9468c65046e6",
  "id": "Tasks_utils.updateTask",
  "pluginId": "js-plugin",
  "pluginType": "JS",
  "unpublishedAction": {
    "actionConfiguration": {
      "encodeParamsToggle": true,
      "jsArguments": [
        {
          "name": "taskId"
        },
        {
          "name": "updateData"
        }
      ],
      "paginationType": "NONE",
      "timeoutInMillisecond": 10000
    },
    "collectionId": "Tasks_utils",
    "confirmBeforeExecute": false,
    "datasource": {
      "isAutoGenerated": false,
      "name": "UNUSED_DATASOURCE",
      "pluginId": "js-plugin"
    },
    "dynamicBindingPathList": [
      {
        "key": "body"
      }
    ],
    "fullyQualifiedName": "utils.updateTask",
    "name": "updateTask",
    "pageId": "Tasks",
    "runBehaviour": "MANUAL",
    "userSetOnLoad": false
  }
}